Metadata-Version: 2.1
Name: modelyst-sqlmodel
Version: 0.0.9
Summary: SQLModel, SQL databases in Python, designed for simplicity, compatibility, and robustness.
Home-page: https://github.com/tiangolo/sqlmodel
License: MIT
Author: Sebastián Ramírez
Author-email: tiangolo@gmail.com
Requires-Python: >=3.6.1,<4.0.0
Classifier: Development Status :: 4 - Beta
Classifier: Framework :: AsyncIO
Classifier: Intended Audience :: Developers
Classifier: Intended Audience :: Science/Research
Classifier: Intended Audience :: System Administrators
Classifier: License :: OSI Approved :: MIT License
Classifier: Programming Language :: Python :: 3
Classifier: Programming Language :: Python :: 3.7
Classifier: Programming Language :: Python :: 3.8
Classifier: Programming Language :: Python :: 3.9
Classifier: Programming Language :: Python :: 3.10
Classifier: Programming Language :: Python :: 3 :: Only
Classifier: Programming Language :: Python :: 3.6
Classifier: Programming Language :: Python :: 3.7
Classifier: Programming Language :: Python :: 3.8
Classifier: Programming Language :: Python :: 3.9
Classifier: Topic :: Database
Classifier: Topic :: Database :: Database Engines/Servers
Classifier: Topic :: Internet
Classifier: Topic :: Internet :: WWW/HTTP
Classifier: Topic :: Internet :: WWW/HTTP :: HTTP Servers
Classifier: Typing :: Typed
Requires-Dist: SQLAlchemy (>=1.4.17,<1.5.0)
Requires-Dist: pydantic (>=1.8.2,<2.0.0)
Requires-Dist: sqlalchemy2-stubs
Project-URL: Documentation, https://sqlmodel.tiangolo.com
Project-URL: Repository, https://github.com/tiangolo/sqlmodel
